web_extractor/__init__.py
web_extractor/cons.py
web_extractor/utils.py
web_extractor/new_extractor/AuthorExtractor.py
web_extractor/new_extractor/ContentExtractor.py
web_extractor/new_extractor/DescriptionExtractor.py
web_extractor/new_extractor/KeywordsExtractor.py
web_extractor/new_extractor/NewExtractor.py
web_extractor/new_extractor/TimeExtractor.py
web_extractor/new_extractor/TitleExtractor.py
web_extractor/new_extractor/__init__.py
web_extractor/new_extractor/new_utils.py
web_extractor/shop_extractor/KeywordsExtractor.py
web_extractor/shop_extractor/TitleExtractor.py
web_extractor/shop_extractor/__init__.py
web_extractor/shop_extractor/shop_utils.py
web_extractor-0.1.3.dist-info/METADATA
web_extractor-0.1.3.dist-info/WHEEL
web_extractor-0.1.3.dist-info/top_level.txt
web_extractor-0.1.3.dist-info/RECORD
