Metadata-Version: 2.1
Name: web-extractor
Version: 0.1.3
Summary: WEB Content Extractor
Home-page: https://github.com/justinzm/WE_pypi
Author: Justin Zm
Author-email: 3907721@qq.com
Maintainer: Justin Zm
Maintainer-email: 3907721@qq.com
License: MIT
Platform: all
Requires-Dist: requests
Requires-Dist: chardet
Requires-Dist: lxml
Requires-Dist: yaml
Requires-Dist: pyyaml
Requires-Dist: numpy
